denodoclient/__init__.py
denodoclient/denodoclient.py
denodoclient/vqlquery.py
denodoclient/dataframes/__init__.py
denodoclient/dataframes/denododataframeclient.py
denodoclient-1.0.1.dist-info/AUTHORS.rst
denodoclient-1.0.1.dist-info/LICENSE
denodoclient-1.0.1.dist-info/METADATA
denodoclient-1.0.1.dist-info/WHEEL
denodoclient-1.0.1.dist-info/top_level.txt
denodoclient-1.0.1.dist-info/RECORD
